pyejabberd/__init__.py
pyejabberd/client.py
pyejabberd/compat.py
pyejabberd/contract.py
pyejabberd/contrib.py
pyejabberd/defaults.py
pyejabberd/definitions.py
pyejabberd/errors.py
pyejabberd/utils.py
pyejabberd/core/__init__.py
pyejabberd/core/arguments.py
pyejabberd/core/definitions.py
pyejabberd/core/errors.py
pyejabberd/core/serializers.py
pyejabberd/muc/__init__.py
pyejabberd/muc/arguments.py
pyejabberd/muc/enums.py
pyejabberd/muc/serializers.py
pyejabberd-0.2.11.dist-info/DESCRIPTION.rst
pyejabberd-0.2.11.dist-info/METADATA
pyejabberd-0.2.11.dist-info/RECORD
pyejabberd-0.2.11.dist-info/WHEEL
pyejabberd-0.2.11.dist-info/metadata.json
pyejabberd-0.2.11.dist-info/top_level.txt
