Metadata-Version: 2.0
Name: pyejabberd
Version: 0.2.11
Summary: A Python client for the Ejabberd XMLRPC API
Home-page: https://github.com/dirkmoors/pyejabberd
Author: Dirk Moors
Author-email: dirkmoors@gmail.com
License: BSD
Keywords: ejabberd,xmlrpc,api,client,xmpp,chat,muc
Platform: UNKNOWN
Classifier: Development Status :: 3 - Alpha
Classifier: Intended Audience :: Developers
Classifier: License :: OSI Approved :: BSD License
Classifier: Operating System :: Unix
Classifier: Operating System :: POSIX
Classifier: Operating System :: Microsoft :: Windows
Classifier: Programming Language :: Python
Classifier: Programming Language :: Python :: 2.6
Classifier: Programming Language :: Python :: 2.7
Classifier: Programming Language :: Python :: 3
Classifier: Programming Language :: Python :: 3.3
Classifier: Programming Language :: Python :: 3.4
Classifier: Programming Language :: Python :: Implementation :: CPython
Classifier: Programming Language :: Python :: Implementation :: PyPy
Classifier: Topic :: Utilities
Requires-Dist: enum34 (==1.1.2)
Requires-Dist: future (==0.15.2)
Requires-Dist: six (==1.9.0)
Requires-Dist: unittest2 (==1.1.0)
